blocks/__init__.py
blocks/base.py
blocks/decorators.py
blocks/meta.py
blocks/pipeline.py
blocks/preprocessing.py
blocks/transformers.py
python_blocks-0.1.10.dist-info/LICENSE
python_blocks-0.1.10.dist-info/METADATA
python_blocks-0.1.10.dist-info/WHEEL
python_blocks-0.1.10.dist-info/RECORD
