Metadata-Version: 2.1
Name: python-blocks
Version: 0.1.10
Summary: Extra blocks for scikit-learn features.
Home-page: https://github.com/ActurialCapital/blocks
License: BSD 3-Clause License
Author: ActurialCapital
Requires-Python: >=3.11,<4.0
Classifier: License :: Other/Proprietary License
Classifier: Programming Language :: Python :: 3
Classifier: Programming Language :: Python :: 3.11
Classifier: Programming Language :: Python :: 3.12
Requires-Dist: imbalanced-learn (>=0.12.3,<0.13.0)
Requires-Dist: numpy (>=1.26.4,<2.0.0)
Requires-Dist: pandas (>=2.2.2,<3.0.0)
Requires-Dist: pandas-ta (>=0.3.14b0,<0.4.0)
Requires-Dist: scikit-learn (>=1.5.0,<2.0.0)
Project-URL: Repository, https://github.com/ActurialCapital/blocks
